MANIFEST.in
README.md
setup.py
caravel/__init__.py
caravel/_version.py
caravel/caravel.py
caravel/caravel_conf.py
caravel/caravel_demo.yaml
caravel/const.py
caravel/exceptions.py
caravel/globs.py
caravel/helpers.py
caravel/looper_parser.py
caravel.egg-info/PKG-INFO
caravel.egg-info/SOURCES.txt
caravel.egg-info/dependency_links.txt
caravel.egg-info/entry_points.txt
caravel.egg-info/requires.txt
caravel.egg-info/top_level.txt
caravel/examples/.DS_Store
caravel/examples/caravel_demo/.DS_Store
caravel/examples/caravel_demo/pipeline_interface.yaml
caravel/examples/caravel_demo/metadata/animals_config.yaml
caravel/examples/caravel_demo/metadata/duplicated_config.yaml
caravel/examples/caravel_demo/metadata/sample_table_animals.csv
caravel/examples/caravel_demo/metadata/sample_table_animals_frog.csv
caravel/examples/caravel_demo/metadata/test.tsv
caravel/examples/caravel_demo/pipeline/demo_pipeline.py
caravel/examples/caravel_demo/pipeline/plotHist.R
caravel/examples/caravel_demo/pipeline/__pycache__/demo_pipeline.cpython-36.pyc
caravel/examples/data/dog1_sounds.txt
caravel/examples/data/dog2_sounds.txt
caravel/examples/data/dog3_sounds.txt
caravel/examples/data/frog1_sounds.txt
caravel/examples/data/frog2_sounds.txt
caravel/examples/data/frog3_sounds.txt
caravel/examples/data/sparrow1_sounds.txt
caravel/examples/data/sparrow2_sounds.txt
caravel/jinja_templates/back_referrer.html
caravel/jinja_templates/caravel.svg
caravel/jinja_templates/compute_info.html
caravel/jinja_templates/error.html
caravel/jinja_templates/execute.html
caravel/jinja_templates/footer.html
caravel/jinja_templates/index.html
caravel/jinja_templates/logo_caravel.html
caravel/jinja_templates/logo_caravel_icon.html
caravel/jinja_templates/logo_looper.html
caravel/jinja_templates/logo_python.html
caravel/jinja_templates/navbar.html
caravel/jinja_templates/options.html
caravel/jinja_templates/preferences.html
caravel/jinja_templates/process.html
caravel/jinja_templates/summary_notice.html
caravel/jinja_templates/template.html
caravel/jinja_templates/top_referrer.html
caravel/requirements/requirements-all.txt
caravel/requirements/requirements-docs.txt
caravel/static/bootstrap.min.css
