Metadata-Version: 1.1
Name: caravel
Version: 0.13.2
Summary: Caravel provides aweb interface to interact with your  PEP-formatted projects. Caravel lets you submit jobs to any cluster resource manager, monitor jobs, summarize results, and browse project summary web pages.
Home-page: https://caravel.databio.org/
Author: Nathan Sheffield, Vince Reuter, Michal Stolarczyk
Author-email: UNKNOWN
License: BSD-2-Clause
Keywords: project,bioinformatics,sequencing,ngs,workflow,GUI
Platform: UNKNOWN
Classifier: Development Status :: 4 - Beta
Classifier: License :: OSI Approved :: BSD License
Classifier: Programming Language :: Python :: 2.7
Classifier: Programming Language :: Python :: 3.5
Classifier: Programming Language :: Python :: 3.6
Classifier: Topic :: Scientific/Engineering :: Bio-Informatics
